mipkit/__init__.py
mipkit/audio.py
mipkit/debug.py
mipkit/downloaders.py
mipkit/fmt.py
mipkit/helpers.py
mipkit/images.py
mipkit/logger.py
mipkit/mprocess.py
mipkit/nest_asyncio.py
mipkit/pdf.py
mipkit/pl_utils.py
mipkit/stats.py
mipkit/utils.py
mipkit/video.py
mipkit/vis.py
mipkit/dl/__init__.py
mipkit/dl/losses.py
mipkit/dl/metrics.py
mipkit/dl/summary.py
mipkit/dl/tune.py
mipkit/dl/utils.py
mipkit/faces/__init__.py
mipkit/faces/faces_utils.py
mipkit/faces/helpers.py
mipkit/ip/__init__.py
mipkit/ip/fft.py
mipkit/ip/freq_filters.py
mipkit/medical/__init__.py
mipkit/medical/itk_snap.py
mipkit/medical/utils.py
mipkit/medical/vis.py
mipkit/nlp/__init__.py
mipkit/nlp/text_cleaner/__init__.py
mipkit/nlp/text_cleaner/cleaner.py
mipkit/nlp/text_cleaner/constants.py
mipkit/nlp/text_cleaner/core.py
mipkit/nlp/text_cleaner/specials.py
mipkit/nlp/text_cleaner/utils.py
mipkit/pytorch/__init__.py
mipkit/pytorch/base.py
mipkit/pytorch/hook.py
mipkit/pytorch/losses.py
mipkit/pytorch/utils.py
mipkit-1.7.2.dist-info/LICENSE
mipkit-1.7.2.dist-info/METADATA
mipkit-1.7.2.dist-info/WHEEL
mipkit-1.7.2.dist-info/entry_points.txt
mipkit-1.7.2.dist-info/top_level.txt
mipkit-1.7.2.dist-info/zip-safe
mipkit-1.7.2.dist-info/RECORD
