Metadata-Version: 2.1
Name: mipkit
Version: 1.7.2
Summary: mipkit
Author: Cong M. Vo
Author-email: congvm.it@gmail.com
License: MIT
Classifier: Programming Language :: Python :: 3
Classifier: License :: OSI Approved :: MIT License
Classifier: Operating System :: OS Independent
Classifier: Topic :: Scientific/Engineering :: Artificial Intelligence
License-File: LICENSE
Requires-Dist: numpy
Requires-Dist: matplotlib
Requires-Dist: tqdm
Requires-Dist: pyyaml
Requires-Dist: termcolor
Requires-Dist: ipdb
Requires-Dist: IPython
Requires-Dist: pyink
Requires-Dist: isort
Requires-Dist: black[jupyter]
